tongopy/__init__.py
tongopy/config_loader.py
tongopy/exceptions.py
tongopy/lang_loader.py
tongopy-1.0.0.dist-info/licenses/LICENSE
tongopy-1.0.0.dist-info/METADATA
tongopy-1.0.0.dist-info/WHEEL
tongopy-1.0.0.dist-info/top_level.txt
tongopy-1.0.0.dist-info/RECORD
