Metadata-Version: 2.4
Name: tongopy
Version: 1.0.0
Summary: Python library that allows you to easily load languages and settings into your project using JSON files
Author-email: "Pedro Agustin Vega (wrrulos)" <pedroagustinvega@proton.me>
License: MIT License
Project-URL: homepage, https://github.com/wrrulosdev/tongopy
Project-URL: documentation, https://github.com/wrrulosdev/tongopy
Project-URL: repository, https://github.com/wrrulosdev/tongopy
Keywords: language,settings,python,json
Classifier: Programming Language :: Python :: 3
Classifier: License :: OSI Approved :: MIT License
Classifier: Operating System :: OS Independent
Requires-Python: >=3.6
License-File: LICENSE
Requires-Dist: aiofiles
Dynamic: license-file
